vra_iaas/__init__.py
vra_iaas/_base_client.py
vra_iaas/_client.py
vra_iaas/_compat.py
vra_iaas/_constants.py
vra_iaas/_exceptions.py
vra_iaas/_files.py
vra_iaas/_models.py
vra_iaas/_qs.py
vra_iaas/_resource.py
vra_iaas/_response.py
vra_iaas/_streaming.py
vra_iaas/_types.py
vra_iaas/_version.py
vra_iaas/py.typed
vra_iaas/_utils/__init__.py
vra_iaas/_utils/_compat.py
vra_iaas/_utils/_datetime_parse.py
vra_iaas/_utils/_logs.py
vra_iaas/_utils/_proxy.py
vra_iaas/_utils/_reflection.py
vra_iaas/_utils/_resources_proxy.py
vra_iaas/_utils/_streams.py
vra_iaas/_utils/_sync.py
vra_iaas/_utils/_transform.py
vra_iaas/_utils/_typing.py
vra_iaas/_utils/_utils.py
vra_iaas/lib/.keep
vra_iaas/resources/__init__.py
vra_iaas/resources/iaas/__init__.py
vra_iaas/resources/iaas/iaas.py
vra_iaas/resources/iaas/api/__init__.py
vra_iaas/resources/iaas/api/api.py
vra_iaas/resources/iaas/api/cloud_accounts_avilb.py
vra_iaas/resources/iaas/api/cloud_accounts_aws.py
vra_iaas/resources/iaas/api/cloud_accounts_azure.py
vra_iaas/resources/iaas/api/cloud_accounts_gcp.py
vra_iaas/resources/iaas/api/cloud_accounts_nsx_t.py
vra_iaas/resources/iaas/api/cloud_accounts_nsx_v.py
vra_iaas/resources/iaas/api/cloud_accounts_vcf.py
vra_iaas/resources/iaas/api/cloud_accounts_vmc.py
vra_iaas/resources/iaas/api/cloud_accounts_vsphere.py
vra_iaas/resources/iaas/api/compute_gateways.py
vra_iaas/resources/iaas/api/configuration_properties.py
vra_iaas/resources/iaas/api/data_collectors.py
vra_iaas/resources/iaas/api/deployments.py
vra_iaas/resources/iaas/api/external_ip_blocks.py
vra_iaas/resources/iaas/api/external_network_ip_ranges.py
vra_iaas/resources/iaas/api/fabric_azure_storage_accounts.py
vra_iaas/resources/iaas/api/fabric_computes.py
vra_iaas/resources/iaas/api/fabric_images.py
vra_iaas/resources/iaas/api/fabric_networks.py
vra_iaas/resources/iaas/api/fabric_networks_vsphere.py
vra_iaas/resources/iaas/api/fabric_vsphere_datastores.py
vra_iaas/resources/iaas/api/fabric_vsphere_storage_policies.py
vra_iaas-0.0.3.dist-info/METADATA
vra_iaas-0.0.3.dist-info/WHEEL
vra_iaas-0.0.3.dist-info/licenses/LICENSE
vra_iaas-0.0.3.dist-info/RECORD
